yes_or_no/LICENSE
yes_or_no/__init__.py
yes_or_no/yes_or_no.py
yes_or_no-1.0.0.dist-info/METADATA
yes_or_no-1.0.0.dist-info/WHEEL
yes_or_no-1.0.0.dist-info/RECORD
