Metadata-Version: 2.1
Name: yes-or-no
Version: 1.0.0
Summary: A silly little helper function, that is strangly helpful. All it does, is prompt a yes or question, then convert a boolean to the answer of yes or now. This library is meant to be used in debug strings, it is recommended to use in multi line f string meant to be passed to a log.debug. It mean to help make understanding the state just a little easier.
License: Apache 2.0
Author: Daniel Davee
Requires-Python: >=3.8,<4.0
Classifier: License :: Other/Proprietary License
Classifier: Programming Language :: Python :: 3
Classifier: Programming Language :: Python :: 3.8
Classifier: Programming Language :: Python :: 3.9
Classifier: Programming Language :: Python :: 3.10
Classifier: Programming Language :: Python :: 3.11
Requires-Dist: chat-companion (>=0.1.6,<0.2.0)
